[{"id":"63.03.01","regency_id":"63.03","name":"Aluh Aluh"},{"id":"63.03.02","regency_id":"63.03","name":"Kertak Hanyar"},{"id":"63.03.03","regency_id":"63.03","name":"Gambut"},{"id":"63.03.04","regency_id":"63.03","name":"Sungai Tabuk"},{"id":"63.03.05","regency_id":"63.03","name":"Martapura"},{"id":"63.03.06","regency_id":"63.03","name":"Karang Intan"},{"id":"63.03.07","regency_id":"63.03","name":"Astambul"},{"id":"63.03.08","regency_id":"63.03","name":"Simpang Empat"},{"id":"63.03.09","regency_id":"63.03","name":"Pengaron"},{"id":"63.03.10","regency_id":"63.03","name":"Sungai Pinang"},{"id":"63.03.11","regency_id":"63.03","name":"Aranio"},{"id":"63.03.12","regency_id":"63.03","name":"Mataraman"},{"id":"63.03.13","regency_id":"63.03","name":"Beruntung Baru"},{"id":"63.03.14","regency_id":"63.03","name":"Martapura Barat"},{"id":"63.03.15","regency_id":"63.03","name":"Martapura Timur"},{"id":"63.03.16","regency_id":"63.03","name":"Sambung Makmur"},{"id":"63.03.17","regency_id":"63.03","name":"Paramasan"},{"id":"63.03.18","regency_id":"63.03","name":"Telaga Bauntung"},{"id":"63.03.19","regency_id":"63.03","name":"Tatah Makmur"},{"id":"63.03.20","regency_id":"63.03","name":"Cintapuri Darussalam"}]