[{"id":"82.05.01","regency_id":"82.05","name":"Mangoli Timur"},{"id":"82.05.02","regency_id":"82.05","name":"Sanana"},{"id":"82.05.03","regency_id":"82.05","name":"Sulabesi Barat"},{"id":"82.05.06","regency_id":"82.05","name":"Mangoli Barat"},{"id":"82.05.07","regency_id":"82.05","name":"Sulabesi Tengah"},{"id":"82.05.08","regency_id":"82.05","name":"Sulabesi Timur"},{"id":"82.05.09","regency_id":"82.05","name":"Sulabesi Selatan"},{"id":"82.05.10","regency_id":"82.05","name":"Mangoli Utara Timur"},{"id":"82.05.11","regency_id":"82.05","name":"Mangoli Tengah"},{"id":"82.05.12","regency_id":"82.05","name":"Mangoli Selatan"},{"id":"82.05.13","regency_id":"82.05","name":"Mangoli Utara"},{"id":"82.05.18","regency_id":"82.05","name":"Sanana Utara"}]